ibis_gizmosql/__init__.py
ibis_gizmosql/converter.py
ibis_gizmosql-0.0.14.dist-info/licenses/LICENSE
ibis_gizmosql-0.0.14.dist-info/METADATA
ibis_gizmosql-0.0.14.dist-info/WHEEL
ibis_gizmosql-0.0.14.dist-info/entry_points.txt
ibis_gizmosql-0.0.14.dist-info/top_level.txt
ibis_gizmosql-0.0.14.dist-info/RECORD
