Metadata-Version: 2.4
Name: ibis-gizmosql
Version: 0.0.14
Summary: An Ibis backend for GizmoSQL
Author-email: Philip Moore <philip@gizmodata.com>
License-Expression: Apache-2.0
Project-URL: Homepage, https://github.com/gizmodata/ibis-gizmosql
Keywords: ibis,gizmosql,ibis-framework,flightsql,duckdb,adbc,gizmodata
Classifier: Programming Language :: Python
Classifier: Programming Language :: Python :: 3
Requires-Python: >=3.10
License-File: LICENSE
Requires-Dist: ibis-framework==11.0.*
Requires-Dist: duckdb==1.4.*
Requires-Dist: adbc-driver-flightsql==1.10.*
Requires-Dist: pyarrow==22.0.*
Requires-Dist: pyarrow-hotfix==0.7
Requires-Dist: numpy==2.3.*
Requires-Dist: packaging==25.0
Requires-Dist: pandas==2.3.*
Requires-Dist: rich==14.2.*
Provides-Extra: test
Requires-Dist: pytest; extra == "test"
Requires-Dist: pytest-snapshot; extra == "test"
Requires-Dist: pytest-mock; extra == "test"
Requires-Dist: filelock; extra == "test"
Requires-Dist: duckdb; extra == "test"
Requires-Dist: dask; extra == "test"
Requires-Dist: distributed; extra == "test"
Requires-Dist: pins[gcs]; extra == "test"
Requires-Dist: docker; extra == "test"
Provides-Extra: dev
Requires-Dist: bumpver; extra == "dev"
Requires-Dist: pandas-stubs==2.3.*; extra == "dev"
Dynamic: license-file
